pyend/__init__.py
pyend/pyend.py
pyend-1.4.23.dist-info/METADATA
pyend-1.4.23.dist-info/WHEEL
pyend-1.4.23.dist-info/entry_points.txt
pyend-1.4.23.dist-info/licenses/LICENSE
pyend-1.4.23.dist-info/RECORD
