Metadata-Version: 2.1
Name: pyend
Version: 1.4.23
Summary: insert block end marks into python code for better formatting and copy paste experience
Project-URL: Homepage, https://github.com/mqnc/pyend
Project-URL: Bug Tracker, https://github.com/mqnc/pyend/issues
Author: mqnc
License-File: LICENSE
Classifier: License :: OSI Approved :: MIT License
Classifier: Operating System :: OS Independent
Classifier: Programming Language :: Python :: 3
Requires-Python: >=3.7
